fw_gear_ants_atlas_registration/__init__.py
fw_gear_ants_atlas_registration/atlas.py
fw_gear_ants_atlas_registration/main.py
fw_gear_ants_atlas_registration/parser.py
fw_gear_ants_atlas_registration/templates/OASIS-30_Atropos_template/Priors2/priors1.nii.gz
fw_gear_ants_atlas_registration/templates/OASIS-30_Atropos_template/Priors2/priors2.nii.gz
fw_gear_ants_atlas_registration/templates/OASIS-30_Atropos_template/Priors2/priors3.nii.gz
fw_gear_ants_atlas_registration/templates/OASIS-30_Atropos_template/Priors2/priors4.nii.gz
fw_gear_ants_atlas_registration/templates/OASIS-30_Atropos_template/Priors2/priors5.nii.gz
fw_gear_ants_atlas_registration/templates/OASIS-30_Atropos_template/Priors2/priors6.nii.gz
fw_gear_ants_atlas_registration/templates/OASIS-30_Atropos_template/README.txt
fw_gear_ants_atlas_registration/templates/OASIS-30_Atropos_template/T_template0.nii.gz
fw_gear_ants_atlas_registration/templates/OASIS-30_Atropos_template/T_template0_BrainCerebellum.nii.gz
fw_gear_ants_atlas_registration/templates/OASIS-30_Atropos_template/T_template0_BrainCerebellumExtractionMask.nii.gz
fw_gear_ants_atlas_registration/templates/OASIS-30_Atropos_template/T_template0_BrainCerebellumMask.nii.gz
fw_gear_ants_atlas_registration/templates/OASIS-30_Atropos_template/T_template0_BrainCerebellumProbabilityMask.nii.gz
fw_gear_ants_atlas_registration/templates/OASIS-30_Atropos_template/T_template0_BrainCerebellumRegistrationMask.nii.gz
fw_gear_ants_atlas_registration/templates/OASIS-30_Atropos_template/T_template0_glm_4labelsJointFusion.nii.gz
fw_gear_ants_atlas_registration/templates/OASIS-30_Atropos_template/T_template0_glm_6labelsJointFusion.nii.gz
fw_gear_ants_atlas_registration/workflow.py
fw_gear_ants_atlas_registration-0.1.1.dist-info/LICENSE
fw_gear_ants_atlas_registration-0.1.1.dist-info/WHEEL
fw_gear_ants_atlas_registration-0.1.1.dist-info/METADATA
fw_gear_ants_atlas_registration-0.1.1.dist-info/RECORD
