Metadata-Version: 2.1
Name: fw-gear-ants-atlas-registration
Version: 0.1.1
Summary: 
Home-page: https://gitlab.com/flywheel-io/flywheel-apps/templates/skeleton
License: MIT
Keywords: Flywheel,Gears
Author: Flywheel
Author-email: support@flywheel.io
Requires-Python: >=3.7,<4.0
Classifier: License :: OSI Approved :: MIT License
Classifier: Programming Language :: Python :: 3
Classifier: Programming Language :: Python :: 3.10
Classifier: Programming Language :: Python :: 3.7
Classifier: Programming Language :: Python :: 3.8
Classifier: Programming Language :: Python :: 3.9
Classifier: Topic :: Scientific/Engineering
Requires-Dist: flywheel-gear-toolkit (>=0.5,<0.6)
Requires-Dist: fw-utils (>=2.0.6,<3.0.0)
Requires-Dist: nipype (>=1.7.0,<2.0.0)
Project-URL: Repository, https://gitlab.com/flywheel-io/flywheel-apps/templates/skeleton
